ndx_conelab/__init__.py
ndx_conelab/conelab_extension.py
ndx_conelab/generator.py
ndx_conelab/extensions/DemoTaskParameters.extensions.yaml
ndx_conelab/extensions/FinalTestParameters.extensions.yaml
ndx_conelab/extensions/SAMPLETASK1.extensions.yaml
ndx_conelab/extensions/UnitTestTaskParameters.extensions.yaml
ndx_conelab/extensions/V2TESTParameters.extensions.yaml
ndx_conelab/extensions/__init__.py
ndx_conelab/spec/conelab.extensions.yaml
ndx_conelab/spec/conelab.namespace.yaml
ndx_conelab-0.2.0.dist-info/licenses/LICENSE
ndx_conelab-0.2.0.dist-info/METADATA
ndx_conelab-0.2.0.dist-info/WHEEL
ndx_conelab-0.2.0.dist-info/entry_points.txt
ndx_conelab-0.2.0.dist-info/top_level.txt
ndx_conelab-0.2.0.dist-info/RECORD
