Metadata-Version: 2.4
Name: ndx-conelab
Version: 0.2.0
Summary: NWB extension for custom Task Parameters used in the Cone Lab.
Author-email: Jose Paulo / Cone Lab <zepaulojr1@gmail.com>
License-Expression: MIT
Project-URL: Homepage, https://github.com/JConeLab/ndx-conelab
Project-URL: Bug Tracker, https://github.com/JConeLab/ndx-conelab/issues
Classifier: Programming Language :: Python :: 3
Classifier: Operating System :: OS Independent
Classifier: Development Status :: 4 - Beta
Classifier: Intended Audience :: Developers
Classifier: Intended Audience :: Science/Research
Classifier: Topic :: Scientific/Engineering
Requires-Python: >=3.8
License-File: LICENSE
Requires-Dist: pynwb>=2.1.0
Requires-Dist: PyYAML>=6.0
Requires-Dist: filelock>=3.4.0
Provides-Extra: test
Requires-Dist: pytest>=7.0; extra == "test"
Provides-Extra: validation
Requires-Dist: jsonschema>=4.0; extra == "validation"
Provides-Extra: dev
Requires-Dist: pytest>=7.0; extra == "dev"
Requires-Dist: jsonschema>=4.0; extra == "dev"
Dynamic: license-file
